setup.py
Topsis/102003253.py
Topsis/__init__.py
Topsis_AnannyaSingh_102003253.egg-info/PKG-INFO
Topsis_AnannyaSingh_102003253.egg-info/SOURCES.txt
Topsis_AnannyaSingh_102003253.egg-info/dependency_links.txt
Topsis_AnannyaSingh_102003253.egg-info/requires.txt
Topsis_AnannyaSingh_102003253.egg-info/top_level.txt