Metadata-Version: 2.1
Name: Topsis-AnannyaSingh-102003253
Version: 1.0
Summary: Python implementation of the Technique for Order of Preference by Similarity to Ideal Solution (TOPSIS)
Home-page: UNKNOWN
Author: Anannya Singh
License: UNKNOWN
Platform: UNKNOWN
